bindepend.py
bindepend-0.1.dist-info/DESCRIPTION.rst
bindepend-0.1.dist-info/METADATA
bindepend-0.1.dist-info/RECORD
bindepend-0.1.dist-info/WHEEL
bindepend-0.1.dist-info/metadata.json
bindepend-0.1.dist-info/top_level.txt
