Metadata-Version: 2.0
Name: bindepend
Version: 0.1
Summary: Binary depedency analysis
Home-page: https://github.com/xoviat/bindepend
Author: Mars Galactic
Author-email: xoviat@users.noreply.github.com
License: GNU GPLv3
Keywords: pyinstaller
Platform: any
Requires-Dist: pefile
